[
  {
    "name": "DANIEL MCDONALD",
    "department": "BIOL",
    "courses": ["BIOL 101 001", "BIOL 101 002"],
    "rating": null,
    "difficulty": null,
    "wouldTakeAgain": null
  },
  {
    "name": "CHRISTOPHER MARTIN",
    "department": "BIOL",
    "courses": ["BIOL 101 003", "BIOL 101L 403"],
    "rating": null,
    "difficulty": null,
    "wouldTakeAgain": null
  },
  {
    "name": "EMILY HARMON",
    "department": "BIOL",
    "courses": ["BIOL 101 004", "BIOL 101L 401", "BIOL 101L 411"],
    "rating": null,
    "difficulty": null,
    "wouldTakeAgain": null
  },
  {
    "name": "JULIE LEBO",
    "department": "BIOL",
    "courses": ["BIOL 101 005", "BIOL 101L 407"],
    "rating": null,
    "difficulty": null,
    "wouldTakeAgain": null
  },
  {
    "name": "SUSAN WHITFIELD",
    "department": "BIOL",
    "courses": ["BIOL 101 006", "BIOL 101 010", "BIOL 101L 412"],
    "rating": null,
    "difficulty": null,
    "wouldTakeAgain": null
  },
  {
    "name": "CHRISTINA ROMERO",
    "department": "BIOL",
    "courses": ["BIOL 101 007", "BIOL 101L 404"],
    "rating": null,
    "difficulty": null,
    "wouldTakeAgain": null
  },
  {
    "name": "JOHN BRADLEY",
    "department": "BIOL",
    "courses": ["BIOL 101 008", "BIOL 101L 408"],
    "rating": null,
    "difficulty": null,
    "wouldTakeAgain": null
  },
  {
    "name": "RACHEL WILLIS",
    "department": "BIOL",
    "courses": ["BIOL 101 009", "BIOL 101L 402"],
    "rating": null,
    "difficulty": null,
    "wouldTakeAgain": null
  },
  {
    "name": "ERIC DEEDS",
    "department": "BIOL",
    "courses": ["BIOL 101H 001"],
    "rating": null,
    "difficulty": null,
    "wouldTakeAgain": null
  },
  {
    "name": "REBECCA FRANKLIN",
    "department": "BIOL",
    "courses": ["BIOL 101L 405"],
    "rating": null,
    "difficulty": null,
    "wouldTakeAgain": null
  },
  {
    "name": "ZACHARY WOLFE",
    "department": "BIOL",
    "courses": ["BIOL 101L 406"],
    "rating": null,
    "difficulty": null,
    "wouldTakeAgain": null
  },
  {
    "name": "LAURA MERSINI",
    "department": "BIOL",
    "courses": ["BIOL 101L 409"],
    "rating": null,
    "difficulty": null,
    "wouldTakeAgain": null
  }
]
